fraud_detection_package_new/__init__.py
fraud_detection_package_new/train_or_predict.py
fraud_detection_package_new/util_functions.py
fraud_detection_package_new-0.1.1.dist-info/LICENSE
fraud_detection_package_new-0.1.1.dist-info/METADATA
fraud_detection_package_new-0.1.1.dist-info/WHEEL
fraud_detection_package_new-0.1.1.dist-info/top_level.txt
fraud_detection_package_new-0.1.1.dist-info/RECORD
