Metadata-Version: 2.1
Name: fraud_detection_package_new
Version: 0.1.1
Summary: A small package to parse and train an ML model. Will update the readme later
Author-email: Vikrant Deshpande <vikdeshp@iu.edu>
Project-URL: Homepage, https://github.com/vikrantdeshpande09876/Credit_Card_Fraud_Detection
Project-URL: Bug Tracker, https://github.com/vikrantdeshpande09876/Credit_Card_Fraud_Detection/issues
Classifier: Programming Language :: Python :: 3
Classifier: License :: OSI Approved :: MIT License
Classifier: Operating System :: OS Independent
Requires-Python: >=3.7
License-File: LICENSE
